<?xml version="1.0" encoding="UTF-8"?>
<castxml2pony xmlns:xi="http://www.w3.org/2001/XInclude">
<xi:include href="./usetypes.xml"/>
<xi:include href="./gtk4.xml"/>
<xi:include href="./use.xml"/>
<xi:include href="./Gtk-4.0.gir"/>
<renderuses>
  <renderuse id="_17674" render="0"/><!-- gtk_column_view_get_type -->
  <renderuse id="_17675" render="0"/><!-- gtk_column_view_new -->
  <renderuse id="_17676" render="0"/><!-- gtk_column_view_get_columns -->
  <renderuse id="_17677" render="0"/><!-- gtk_column_view_append_column -->
  <renderuse id="_17678" render="0"/><!-- gtk_column_view_remove_column -->
  <renderuse id="_17679" render="0"/><!-- gtk_column_view_insert_column -->
  <renderuse id="_17680" render="0"/><!-- gtk_column_view_get_model -->
  <renderuse id="_17681" render="0"/><!-- gtk_column_view_set_model -->
  <renderuse id="_17682" render="0"/><!-- gtk_column_view_get_show_row_separators -->
  <renderuse id="_17683" render="0"/><!-- gtk_column_view_set_show_row_separators -->
  <renderuse id="_17684" render="0"/><!-- gtk_column_view_get_show_column_separators -->
  <renderuse id="_17685" render="0"/><!-- gtk_column_view_set_show_column_separators -->
  <renderuse id="_17686" render="0"/><!-- gtk_column_view_get_sorter -->
  <renderuse id="_17687" render="0"/><!-- gtk_column_view_sort_by_column -->
  <renderuse id="_17688" render="0"/><!-- gtk_column_view_set_single_click_activate -->
  <renderuse id="_17689" render="0"/><!-- gtk_column_view_get_single_click_activate -->
  <renderuse id="_17690" render="0"/><!-- gtk_column_view_set_reorderable -->
  <renderuse id="_17691" render="0"/><!-- gtk_column_view_get_reorderable -->
  <renderuse id="_17692" render="0"/><!-- gtk_column_view_set_enable_rubberband -->
  <renderuse id="_17693" render="0"/><!-- gtk_column_view_get_enable_rubberband -->
  <renderuse id="_17696" render="0"/><!-- gtk_column_view_column_get_type -->
  <renderuse id="_17697" render="0"/><!-- gtk_column_view_column_new -->
  <renderuse id="_17698" render="0"/><!-- gtk_column_view_column_get_column_view -->
  <renderuse id="_17699" render="0"/><!-- gtk_column_view_column_set_factory -->
  <renderuse id="_17700" render="0"/><!-- gtk_column_view_column_get_factory -->
  <renderuse id="_17701" render="0"/><!-- gtk_column_view_column_set_title -->
  <renderuse id="_17702" render="0"/><!-- gtk_column_view_column_get_title -->
  <renderuse id="_17703" render="0"/><!-- gtk_column_view_column_set_sorter -->
  <renderuse id="_17704" render="0"/><!-- gtk_column_view_column_get_sorter -->
  <renderuse id="_17705" render="0"/><!-- gtk_column_view_column_set_visible -->
  <renderuse id="_17706" render="0"/><!-- gtk_column_view_column_get_visible -->
  <renderuse id="_17707" render="0"/><!-- gtk_column_view_column_set_header_menu -->
  <renderuse id="_17708" render="0"/><!-- gtk_column_view_column_get_header_menu -->
  <renderuse id="_17709" render="0"/><!-- gtk_column_view_column_set_fixed_width -->
  <renderuse id="_17710" render="0"/><!-- gtk_column_view_column_get_fixed_width -->
  <renderuse id="_17711" render="0"/><!-- gtk_column_view_column_set_resizable -->
  <renderuse id="_17712" render="0"/><!-- gtk_column_view_column_get_resizable -->
  <renderuse id="_17713" render="0"/><!-- gtk_column_view_column_set_expand -->
  <renderuse id="_17714" render="0"/><!-- gtk_column_view_column_get_expand -->
</renderuses>
</castxml2pony>
