<?xml version="1.0" encoding="UTF-8"?>
<castxml2pony xmlns:xi="http://www.w3.org/2001/XInclude">
<xi:include href="./usetypes.xml"/>
<xi:include href="./gtk4.xml"/>
<xi:include href="./use.xml"/>
<xi:include href="./Gtk-4.0.gir"/>
<renderuses>
  <renderuse id="_16838" render="0"/><!-- gtk_bookmark_list_get_type -->
  <renderuse id="_16863" render="0"/><!-- gtk_bookmark_list_new -->
  <renderuse id="_16864" render="0"/><!-- gtk_bookmark_list_get_filename -->
  <renderuse id="_16865" render="0"/><!-- gtk_bookmark_list_set_attributes -->
  <renderuse id="_16866" render="0"/><!-- gtk_bookmark_list_get_attributes -->
  <renderuse id="_16867" render="0"/><!-- gtk_bookmark_list_set_io_priority -->
  <renderuse id="_16868" render="0"/><!-- gtk_bookmark_list_get_io_priority -->
  <renderuse id="_16869" render="0"/><!-- gtk_bookmark_list_is_loading -->
</renderuses>
</castxml2pony>
